namedout/dbglibnames.py
namedout/test.py
namedout/__init__.py
namedout-1.1.dist-info/DESCRIPTION.rst
namedout-1.1.dist-info/METADATA
namedout-1.1.dist-info/metadata.json
namedout-1.1.dist-info/RECORD
namedout-1.1.dist-info/top_level.txt
namedout-1.1.dist-info/WHEEL
