Metadata-Version: 2.0
Name: namedout
Version: 1.1
Summary: write values (and their names) to stdout in python script
Home-page: UNKNOWN
Author: Ivan Bykov
Author-email: ivan.bykov@gmail.com
License: Python license
Platform: python 2.7
Classifier: Natural Language :: Russian
Classifier: License :: OSI Approved :: Python Software Foundation License
Requires-Dist: astunparse
